catch_pdm.srcs/sources_1/new/uart_tx.v
module uart_tx 
  #( parameter CLKS_PER_BIT = 0)
  (
   input       i_Clock,
   input       i_Tx_DV,
   input [7:0] i_Tx_Byte, 
   output      o_Tx_Active,
   output reg  o_Tx_Serial,
   output      o_Tx_Done
   );
  
  parameter s_IDLE         = 3'b000;
  parameter s_TX_START_BIT = 3'b001;
  parameter s_TX_DATA_BITS = 3'b010;
  parameter s_TX_STOP_BIT  = 3'b011;
  parameter s_CLEANUP      = 3'b100;
   
  reg [2:0]    r_SM_Main     = 0;
  reg [7:0]    r_Clock_Count = 0;
  reg [2:0]    r_Bit_Index   = 0;
  reg [7:0]    r_Tx_Data     = 0;
  reg          r_Tx_Done     = 0;
  reg          r_Tx_Active   = 0;
     
  always @(posedge i_Clock)
    begin
       
      case (r_SM_Main)
        s_IDLE :
          begin
            o_Tx_Serial   <= 1'b1;         // Drive Line High for Idle
            r_Tx_Done     <= 1'b0;
            r_Clock_Count <= 0;
            r_Bit_Index   <= 0;
             
            if (i_Tx_DV == 1'b1)
              begin
                r_Tx_Active <= 1'b1;
                r_Tx_Data   <= i_Tx_Byte;
                r_SM_Main   <= s_TX_START_BIT;
              end
            else
              r_SM_Main <= s_IDLE;
          end // case: s_IDLE
         
         
        // Send out Start Bit. Start bit = 0
        s_TX_START_BIT :
          begin
            o_Tx_Serial <= 1'b0;
             
            // Wait CLKS_PER_BIT-1 clock cycles for start bit to finish
            if (r_Clock_Count < CLKS_PER_BIT-1)
              begin
                r_Clock_Count <= r_Clock_Count + 1;
                r_SM_Main     <= s_TX_START_BIT;
              end
            else
              begin
                r_Clock_Count <= 0;
                r_SM_Main     <= s_TX_DATA_BITS;
              end
          end // case: s_TX_START_BIT
         
         
        // Wait CLKS_PER_BIT-1 clock cycles for data bits to finish         
        s_TX_DATA_BITS :
          begin
            o_Tx_Serial <= r_Tx_Data[r_Bit_Index];
             
            if (r_Clock_Count < CLKS_PER_BIT-1)
              begin
                r_Clock_Count <= r_Clock_Count + 1;
                r_SM_Main     <= s_TX_DATA_BITS;
              end
            else
              begin
                r_Clock_Count <= 0;
                 
                // Check if we have sent out all bits
                if (r_Bit_Index < 7)
                  begin
                    r_Bit_Index <= r_Bit_Index + 1;
                    r_SM_Main   <= s_TX_DATA_BITS;
                  end
                else
                  begin
                    r_Bit_Index <= 0;
                    r_SM_Main   <= s_TX_STOP_BIT;
                  end
              end
          end // case: s_TX_DATA_BITS
         
         
        // Send out Stop bit.  Stop bit = 1
        s_TX_STOP_BIT :
          begin
            o_Tx_Serial <= 1'b1;
             
            // Wait CLKS_PER_BIT-1 clock cycles for Stop bit to finish
            if (r_Clock_Count < CLKS_PER_BIT-1)
              begin
                r_Clock_Count <= r_Clock_Count + 1;
                r_SM_Main     <= s_TX_STOP_BIT;
              end
            else
              begin
                r_Tx_Done     <= 1'b1;
                r_Clock_Count <= 0;
                r_SM_Main     <= s_CLEANUP;
                r_Tx_Active   <= 1'b0;
              end
          end // case: s_Tx_STOP_BIT
         
         
        // Stay here 1 clock
        s_CLEANUP :
          begin
            r_Tx_Done <= 1'b1;
            r_SM_Main <= s_IDLE;
          end
         
         
        default :
          r_SM_Main <= s_IDLE;
         
      endcase
    end
 
  assign o_Tx_Active = r_Tx_Active;
  assign o_Tx_Done   = r_Tx_Done;
   
endmodule

catch_pdm.srcs/sources_1/new/uart_rx.v
module uart_rx 
  #(parameter CLKS_PER_BIT = 0)
  (
   input        i_Clock,
   input        i_Rx_Serial,
   output       o_Rx_DV,
   output [7:0] o_Rx_Byte
   );
    
  parameter s_IDLE         = 3'b000;
  parameter s_RX_START_BIT = 3'b001;
  parameter s_RX_DATA_BITS = 3'b010;
  parameter s_RX_STOP_BIT  = 3'b011;
  parameter s_CLEANUP      = 3'b100;
   
  reg           r_Rx_Data_R = 1'b1;
  reg           r_Rx_Data   = 1'b1;
   
  reg [7:0]     r_Clock_Count = 0;
  reg [2:0]     r_Bit_Index   = 0; //8 bits total
  reg [7:0]     r_Rx_Byte     = 0;
  reg           r_Rx_DV       = 0;
  reg [2:0]     r_SM_Main     = 0;
   
  // Purpose: Double-register the incoming data.
  // This allows it to be used in the UART RX Clock Domain.
  // (It removes problems caused by metastability)
  always @(posedge i_Clock)
    begin
      r_Rx_Data_R <= i_Rx_Serial;
      r_Rx_Data   <= r_Rx_Data_R;
    end
   
   
  // Purpose: Control RX state machine
  always @(posedge i_Clock)
    begin
       
      case (r_SM_Main)
        s_IDLE :
          begin
            r_Rx_DV       <= 1'b0;
            r_Clock_Count <= 0;
            r_Bit_Index   <= 0;
             
            if (r_Rx_Data == 1'b0)          // Start bit detected
              r_SM_Main <= s_RX_START_BIT;
            else
              r_SM_Main <= s_IDLE;
          end
         
        // Check middle of start bit to make sure it's still low
        s_RX_START_BIT :
          begin
            if (r_Clock_Count == (CLKS_PER_BIT-1)/2)
              begin
                if (r_Rx_Data == 1'b0)
                  begin
                    r_Clock_Count <= 0;  // reset counter, found the middle
                    r_SM_Main     <= s_RX_DATA_BITS;
                  end
                else
                  r_SM_Main <= s_IDLE;
              end
            else
              begin
                r_Clock_Count <= r_Clock_Count + 1;
                r_SM_Main     <= s_RX_START_BIT;
              end
          end // case: s_RX_START_BIT
         
         
        // Wait CLKS_PER_BIT-1 clock cycles to sample serial data
        s_RX_DATA_BITS :
          begin
            if (r_Clock_Count < CLKS_PER_BIT-1)
              begin
                r_Clock_Count <= r_Clock_Count + 1;
                r_SM_Main     <= s_RX_DATA_BITS;
              end
            else
              begin
                r_Clock_Count          <= 0;
                r_Rx_Byte[r_Bit_Index] <= r_Rx_Data;
                 
                // Check if we have received all bits
                if (r_Bit_Index < 7)
                  begin
                    r_Bit_Index <= r_Bit_Index + 1;
                    r_SM_Main   <= s_RX_DATA_BITS;
                  end
                else
                  begin
                    r_Bit_Index <= 0;
                    r_SM_Main   <= s_RX_STOP_BIT;
                  end
              end
          end // case: s_RX_DATA_BITS
     
     
        // Receive Stop bit.  Stop bit = 1
        s_RX_STOP_BIT :
          begin
            // Wait CLKS_PER_BIT-1 clock cycles for Stop bit to finish
            if (r_Clock_Count < CLKS_PER_BIT-1)
              begin
                r_Clock_Count <= r_Clock_Count + 1;
                r_SM_Main     <= s_RX_STOP_BIT;
              end
            else
              begin
                r_Rx_DV       <= 1'b1;
                r_Clock_Count <= 0;
                r_SM_Main     <= s_CLEANUP;
              end
          end // case: s_RX_STOP_BIT
     
         
        // Stay here 1 clock
        s_CLEANUP :
          begin
            r_SM_Main <= s_IDLE;
            r_Rx_DV   <= 1'b0;
          end
         
         
        default :
          r_SM_Main <= s_IDLE;
         
      endcase
    end   
   
  assign o_Rx_DV   = r_Rx_DV;
  assign o_Rx_Byte = r_Rx_Byte;
   
endmodule // uart_rx

catch_pdm.srcs/sources_1/new/uart_tb.v
`timescale 1ns/10ps
 
`include "uart_tx.v"
`include "uart_rx.v"
 
module uart_tb ();
 
  // Testbench uses a 10 MHz clock
  // Want to interface to 115200 baud UART
  // 10000000 / 115200 = 87 Clocks Per Bit.
  parameter c_CLOCK_PERIOD_NS = 666;  
  parameter c_CLKS_PER_BIT    = 156;  // 1.5M/9600 = 156
  parameter c_BIT_PERIOD      = 102896;
   
  reg r_Clock = 0;
  reg r_Tx_DV = 0;
  wire w_Tx_Done;
  reg [7:0] r_Tx_Byte = 0;
  reg r_Rx_Serial = 1;
  wire [7:0] w_Rx_Byte;
   
 
  // Takes in input byte and serializes it 
  task UART_WRITE_BYTE;
    input [7:0] i_Data;
    integer     ii;
    begin
       
      // Send Start Bit
      r_Rx_Serial <= 1'b0;
      #(c_BIT_PERIOD);
      #1000;
       
       
      // Send Data Byte
      for (ii=0; ii<8; ii=ii+1)
        begin
          r_Rx_Serial <= i_Data[ii];
          $display("data = %b " , i_Data[ii]);
          #(c_BIT_PERIOD);
        end
       
      // Send Stop Bit
      r_Rx_Serial <= 1'b1;
      #(c_BIT_PERIOD);
     end
  endtask // UART_WRITE_BYTE
   
   
  uart_rx #(.CLKS_PER_BIT(c_CLKS_PER_BIT)) UART_RX_INST
    (.i_Clock(r_Clock),
     .i_Rx_Serial(r_Rx_Serial),
     .o_Rx_DV(),
     .o_Rx_Byte(w_Rx_Byte)
     );
   
  uart_tx #(.CLKS_PER_BIT(c_CLKS_PER_BIT)) UART_TX_INST
    (.i_Clock(r_Clock),
     .i_Tx_DV(r_Tx_DV),
     .i_Tx_Byte(r_Tx_Byte),
     .o_Tx_Active(),
     .o_Tx_Serial(),
     .o_Tx_Done(w_Tx_Done)
     );
 
   
  always
    #(c_CLOCK_PERIOD_NS/2) r_Clock <= !r_Clock;
 
   
  // Main Testing:
  initial
    begin
            $dumpfile("uart");
     $dumpvars;
      // Tell UART to send a command (exercise Tx)
      @(posedge r_Clock);
      @(posedge r_Clock);
      r_Tx_DV <= 1'b1;
      r_Tx_Byte <= 8'hAB;
      @(posedge r_Clock);
      r_Tx_DV <= 1'b0;
      @(posedge w_Tx_Done);
       
      // Send a command to the UART (exercise Rx)
      @(posedge r_Clock);
      UART_WRITE_BYTE(8'h3F);
      @(posedge r_Clock);
             
      // Check that the correct command was received
      if (w_Rx_Byte == 8'h3F)
        $display("Test Passed - Correct Byte Received");
      else
        $display("Test Failed - Incorrect Byte Received");
      
      #1000
      $finish;
    end
   
endmodule

catch_pdm.srcs/sources_1/new/uart.vcd
$date
	Thu Nov 19 15:45:15 2020
$end
$version
	Icarus Verilog
$end
$timescale
	10ps
$end
$scope module uart_tb $end
$var wire 1 ! w_Tx_Done $end
$var wire 8 " w_Rx_Byte [7:0] $end
$var reg 1 # r_Clock $end
$var reg 1 $ r_Rx_Serial $end
$var reg 8 % r_Tx_Byte [7:0] $end
$var reg 1 & r_Tx_DV $end
$scope module UART_RX_INST $end
$var wire 1 # i_Clock $end
$var wire 1 $ i_Rx_Serial $end
$var wire 8 ' o_Rx_Byte [7:0] $end
$var wire 1 ( o_Rx_DV $end
$var reg 3 ) r_Bit_Index [2:0] $end
$var reg 8 * r_Clock_Count [7:0] $end
$var reg 8 + r_Rx_Byte [7:0] $end
$var reg 1 , r_Rx_DV $end
$var reg 1 - r_Rx_Data $end
$var reg 1 . r_Rx_Data_R $end
$var reg 3 / r_SM_Main [2:0] $end
$upscope $end
$scope module UART_TX_INST $end
$var wire 1 # i_Clock $end
$var wire 8 0 i_Tx_Byte [7:0] $end
$var wire 1 & i_Tx_DV $end
$var wire 1 1 o_Tx_Active $end
$var wire 1 ! o_Tx_Done $end
$var reg 1 2 o_Tx_Serial $end
$var reg 3 3 r_Bit_Index [2:0] $end
$var reg 8 4 r_Clock_Count [7:0] $end
$var reg 3 5 r_SM_Main [2:0] $end
$var reg 1 6 r_Tx_Active $end
$var reg 8 7 r_Tx_Data [7:0] $end
$var reg 1 8 r_Tx_Done $end
$upscope $end
$scope task UART_WRITE_BYTE $end
$var reg 8 9 i_Data [7:0] $end
$var integer 32 : ii [31:0] $end
$upscope $end
$upscope $end
$enddefinitions $end
#0
$dumpvars
bx :
bx 9
08
b0 7
06
b0 5
b0 4
b0 3
x2
01
b0 0
b0 /
1.
1-
0,
b0 +
b0 *
b0 )
0(
b0 '
0&
b0 %
1$
0#
b0 "
0!
$end
#33300
12
1#
#66600
0#
#99900
b10101011 %
b10101011 0
1&
1#
#133200
0#
#166500
b1 5
b10101011 7
11
16
0&
1#
#199800
0#
#233100
b1 4
02
1#
#266400
0#
#299700
b10 4
1#
#333000
0#
#366300
b11 4
1#
#399600
0#
#432900
b100 4
1#
#466200
0#
#499500
b101 4
1#
#532800
0#
#566100
b110 4
1#
#599400
0#
#632700
b111 4
1#
#666000
0#
#699300
b1000 4
1#
#732600
0#
#765900
b1001 4
1#
#799200
0#
#832500
b1010 4
1#
#865800
0#
#899100
b1011 4
1#
#932400
0#
#965700
b1100 4
1#
#999000
0#
#1032300
b1101 4
1#
#1065600
0#
#1098900
b1110 4
1#
#1132200
0#
#1165500
b1111 4
1#
#1198800
0#
#1232100
b10000 4
1#
#1265400
0#
#1298700
b10001 4
1#
#1332000
0#
#1365300
b10010 4
1#
#1398600
0#
#1431900
b10011 4
1#
#1465200
0#
#1498500
b10100 4
1#
#1531800
0#
#1565100
b10101 4
1#
#1598400
0#
#1631700
b10110 4
1#
#1665000
0#
#1698300
b10111 4
1#
#1731600
0#
#1764900
b11000 4
1#
#1798200
0#
#1831500
b11001 4
1#
#1864800
0#
#1898100
b11010 4
1#
#1931400
0#
#1964700
b11011 4
1#
#1998000
0#
#2031300
b11100 4
1#
#2064600
0#
#2097900
b11101 4
1#
#2131200
0#
#2164500
b11110 4
1#
#2197800
0#
#2231100
b11111 4
1#
#2264400
0#
#2297700
b100000 4
1#
#2331000
0#
#2364300
b100001 4
1#
#2397600
0#
#2430900
b100010 4
1#
#2464200
0#
#2497500
b100011 4
1#
#2530800
0#
#2564100
b100100 4
1#
#2597400
0#
#2630700
b100101 4
1#
#2664000
0#
#2697300
b100110 4
1#
#2730600
0#
#2763900
b100111 4
1#
#2797200
0#
#2830500
b101000 4
1#
#2863800
0#
#2897100
b101001 4
1#
#2930400
0#
#2963700
b101010 4
1#
#2997000
0#
#3030300
b101011 4
1#
#3063600
0#
#3096900
b101100 4
1#
#3130200
0#
#3163500
b101101 4
1#
#3196800
0#
#3230100
b101110 4
1#
#3263400
0#
#3296700
b101111 4
1#
#3330000
0#
#3363300
b110000 4
1#
#3396600
0#
#3429900
b110001 4
1#
#3463200
0#
#3496500
b110010 4
1#
#3529800
0#
#3563100
b110011 4
1#
#3596400
0#
#3629700
b110100 4
1#
#3663000
0#
#3696300
b110101 4
1#
#3729600
0#
#3762900
b110110 4
1#
#3796200
0#
#3829500
b110111 4
1#
#3862800
0#
#3896100
b111000 4
1#
#3929400
0#
#3962700
b111001 4
1#
#3996000
0#
#4029300
b111010 4
1#
#4062600
0#
#4095900
b111011 4
1#
#4129200
0#
#4162500
b111100 4
1#
#4195800
0#
#4229100
b111101 4
1#
#4262400
0#
#4295700
b111110 4
1#
#4329000
0#
#4362300
b111111 4
1#
#4395600
0#
#4428900
b1000000 4
1#
#4462200
0#
#4495500
b1000001 4
1#
#4528800
0#
#4562100
b1000010 4
1#
#4595400
0#
#4628700
b1000011 4
1#
#4662000
0#
#4695300
b1000100 4
1#
#4728600
0#
#4761900
b1000101 4
1#
#4795200
0#
#4828500
b1000110 4
1#
#4861800
0#
#4895100
b1000111 4
1#
#4928400
0#
#4961700
b1001000 4
1#
#4995000
0#
#5028300
b1001001 4
1#
#5061600
0#
#5094900
b1001010 4
1#
#5128200
0#
#5161500
b1001011 4
1#
#5194800
0#
#5228100
b1001100 4
1#
#5261400
0#
#5294700
b1001101 4
1#
#5328000
0#
#5361300
b1001110 4
1#
#5394600
0#
#5427900
b1001111 4
1#
#5461200
0#
#5494500
b1010000 4
1#
#5527800
0#
#5561100
b1010001 4
1#
#5594400
0#
#5627700
b1010010 4
1#
#5661000
0#
#5694300
b1010011 4
1#
#5727600
0#
#5760900
b1010100 4
1#
#5794200
0#
#5827500
b1010101 4
1#
#5860800
0#
#5894100
b1010110 4
1#
#5927400
0#
#5960700
b1010111 4
1#
#5994000
0#
#6027300
b1011000 4
1#
#6060600
0#
#6093900
b1011001 4
1#
#6127200
0#
#6160500
b1011010 4
1#
#6193800
0#
#6227100
b1011011 4
1#
#6260400
0#
#6293700
b1011100 4
1#
#6327000
0#
#6360300
b1011101 4
1#
#6393600
0#
#6426900
b1011110 4
1#
#6460200
0#
#6493500
b1011111 4
1#
#6526800
0#
#6560100
b1100000 4
1#
#6593400
0#
#6626700
b1100001 4
1#
#6660000
0#
#6693300
b1100010 4
1#
#6726600
0#
#6759900
b1100011 4
1#
#6793200
0#
#6826500
b1100100 4
1#
#6859800
0#
#6893100
b1100101 4
1#
#6926400
0#
#6959700
b1100110 4
1#
#6993000
0#
#7026300
b1100111 4
1#
#7059600
0#
#7092900
b1101000 4
1#
#7126200
0#
#7159500
b1101001 4
1#
#7192800
0#
#7226100
b1101010 4
1#
#7259400
0#
#7292700
b1101011 4
1#
#7326000
0#
#7359300
b1101100 4
1#
#7392600
0#
#7425900
b1101101 4
1#
#7459200
0#
#7492500
b1101110 4
1#
#7525800
0#
#7559100
b1101111 4
1#
#7592400
0#
#7625700
b1110000 4
1#
#7659000
0#
#7692300
b1110001 4
1#
#7725600
0#
#7758900
b1110010 4
1#
#7792200
0#
#7825500
b1110011 4
1#
#7858800
0#
#7892100
b1110100 4
1#
#7925400
0#
#7958700
b1110101 4
1#
#7992000
0#
#8025300
b1110110 4
1#
#8058600
0#
#8091900
b1110111 4
1#
#8125200
0#
#8158500
b1111000 4
1#
#8191800
0#
#8225100
b1111001 4
1#
#8258400
0#
#8291700
b1111010 4
1#
#8325000
0#
#8358300
b1111011 4
1#
#8391600
0#
#8424900
b1111100 4
1#
#8458200
0#
#8491500
b1111101 4
1#
#8524800
0#
#8558100
b1111110 4
1#
#8591400
0#
#8624700
b1111111 4
1#
#8658000
0#
#8691300
b10000000 4
1#
#8724600
0#
#8757900
b10000001 4
1#
#8791200
0#
#8824500
b10000010 4
1#
#8857800
0#
#8891100
b10000011 4
1#
#8924400
0#
#8957700
b10000100 4
1#
#8991000
0#
#9024300
b10000101 4
1#
#9057600
0#
#9090900
b10000110 4
1#
#9124200
0#
#9157500
b10000111 4
1#
#9190800
0#
#9224100
b10001000 4
1#
#9257400
0#
#9290700
b10001001 4
1#
#9324000
0#
#9357300
b10001010 4
1#
#9390600
0#
#9423900
b10001011 4
1#
#9457200
0#
#9490500
b10001100 4
1#
#9523800
0#
#9557100
b10001101 4
1#
#9590400
0#
#9623700
b10001110 4
1#
#9657000
0#
#9690300
b10001111 4
1#
#9723600
0#
#9756900
b10010000 4
1#
#9790200
0#
#9823500
b10010001 4
1#
#9856800
0#
#9890100
b10010010 4
1#
#9923400
0#
#9956700
b10010011 4
1#
#9990000
0#
#10023300
b10010100 4
1#
#10056600
0#
#10089900
b10010101 4
1#
#10123200
0#
#10156500
b10010110 4
1#
#10189800
0#
#10223100
b10010111 4
1#
#10256400
0#
#10289700
b10011000 4
1#
#10323000
0#
#10356300
b10011001 4
1#
#10389600
0#
#10422900
b10011010 4
1#
#10456200
0#
#10489500
b10011011 4
1#
#10522800
0#
#10556100
b10 5
b0 4
1#
#10589400
0#
#10622700
b1 4
12
1#
#10656000
0#
#10689300
b10 4
1#
#10722600
0#
#10755900
b11 4
1#
#10789200
0#
#10822500
b100 4
1#
#10855800
0#
#10889100
b101 4
1#
#10922400
0#
#10955700
b110 4
1#
#10989000
0#
#11022300
b111 4
1#
#11055600
0#
#11088900
b1000 4
1#
#11122200
0#
#11155500
b1001 4
1#
#11188800
0#
#11222100
b1010 4
1#
#11255400
0#
#11288700
b1011 4
1#
#11322000
0#
#11355300
b1100 4
1#
#11388600
0#
#11421900
b1101 4
1#
#11455200
0#
#11488500
b1110 4
1#
#11521800
0#
#11555100
b1111 4
1#
#11588400
0#
#11621700
b10000 4
1#
#11655000
0#
#11688300
b10001 4
1#
#11721600
0#
#11754900
b10010 4
1#
#11788200
0#
#11821500
b10011 4
1#
#11854800
0#
#11888100
b10100 4
1#
#11921400
0#
#11954700
b10101 4
1#
#11988000
0#
#12021300
b10110 4
1#
#12054600
0#
#12087900
b10111 4
1#
#12121200
0#
#12154500
b11000 4
1#
#12187800
0#
#12221100
b11001 4
1#
#12254400
0#
#12287700
b11010 4
1#
#12321000
0#
#12354300
b11011 4
1#
#12387600
0#
#12420900
b11100 4
1#
#12454200
0#
#12487500
b11101 4
1#
#12520800
0#
#12554100
b11110 4
1#
#12587400
0#
#12620700
b11111 4
1#
#12654000
0#
#12687300
b100000 4
1#
#12720600
0#
#12753900
b100001 4
1#
#12787200
0#
#12820500
b100010 4
1#
#12853800
0#
#12887100
b100011 4
1#
#12920400
0#
#12953700
b100100 4
1#
#12987000
0#
#13020300
b100101 4
1#
#13053600
0#
#13086900
b100110 4
1#
#13120200
0#
#13153500
b100111 4
1#
#13186800
0#
#13220100
b101000 4
1#
#13253400
0#
#13286700
b101001 4
1#
#13320000
0#
#13353300
b101010 4
1#
#13386600
0#
#13419900
b101011 4
1#
#13453200
0#
#13486500
b101100 4
1#
#13519800
0#
#13553100
b101101 4
1#
#13586400
0#
#13619700
b101110 4
1#
#13653000
0#
#13686300
b101111 4
1#
#13719600
0#
#13752900
b110000 4
1#
#13786200
0#
#13819500
b110001 4
1#
#13852800
0#
#13886100
b110010 4
1#
#13919400
0#
#13952700
b110011 4
1#
#13986000
0#
#14019300
b110100 4
1#
#14052600
0#
#14085900
b110101 4
1#
#14119200
0#
#14152500
b110110 4
1#
#14185800
0#
#14219100
b110111 4
1#
#14252400
0#
#14285700
b111000 4
1#
#14319000
0#
#14352300
b111001 4
1#
#14385600
0#
#14418900
b111010 4
1#
#14452200
0#
#14485500
b111011 4
1#
#14518800
0#
#14552100
b111100 4
1#
#14585400
0#
#14618700
b111101 4
1#
#14652000
0#
#14685300
b111110 4
1#
#14718600
0#
#14751900
b111111 4
1#
#14785200
0#
#14818500
b1000000 4
1#
#14851800
0#
#14885100
b1000001 4
1#
#14918400
0#
#14951700
b1000010 4
1#
#14985000
0#
#15018300
b1000011 4
1#
#15051600
0#
#15084900
b1000100 4
1#
#15118200
0#
#15151500
b1000101 4
1#
#15184800
0#
#15218100
b1000110 4
1#
#15251400
0#
#15284700
b1000111 4
1#
#15318000
0#
#15351300
b1001000 4
1#
#15384600
0#
#15417900
b1001001 4
1#
#15451200
0#
#15484500
b1001010 4
1#
#15517800
0#
#15551100
b1001011 4
1#
#15584400
0#
#15617700
b1001100 4
1#
#15651000
0#
#15684300
b1001101 4
1#
#15717600
0#
#15750900
b1001110 4
1#
#15784200
0#
#15817500
b1001111 4
1#
#15850800
0#
#15884100
b1010000 4
1#
#15917400
0#
#15950700
b1010001 4
1#
#15984000
0#
#16017300
b1010010 4
1#
#16050600
0#
#16083900
b1010011 4
1#
#16117200
0#
#16150500
b1010100 4
1#
#16183800
0#
#16217100
b1010101 4
1#
#16250400
0#
#16283700
b1010110 4
1#
#16317000
0#
#16350300
b1010111 4
1#
#16383600
0#
#16416900
b1011000 4
1#
#16450200
0#
#16483500
b1011001 4
1#
#16516800
0#
#16550100
b1011010 4
1#
#16583400
0#
#16616700
b1011011 4
1#
#16650000
0#
#16683300
b1011100 4
1#
#16716600
0#
#16749900
b1011101 4
1#
#16783200
0#
#16816500
b1011110 4
1#
#16849800
0#
#16883100
b1011111 4
1#
#16916400
0#
#16949700
b1100000 4
1#
#16983000
0#
#17016300
b1100001 4
1#
#17049600
0#
#17082900
b1100010 4
1#
#17116200
0#
#17149500
b1100011 4
1#
#17182800
0#
#17216100
b1100100 4
1#
#17249400
0#
#17282700
b1100101 4
1#
#17316000
0#
#17349300
b1100110 4
1#
#17382600
0#
#17415900
b1100111 4
1#
#17449200
0#
#17482500
b1101000 4
1#
#17515800
0#
#17549100
b1101001 4
1#
#17582400
0#
#17615700
b1101010 4
1#
#17649000
0#
#17682300
b1101011 4
1#
#17715600
0#
#17748900
b1101100 4
1#
#17782200
0#
#17815500
b1101101 4
1#
#17848800
0#
#17882100
b1101110 4
1#
#17915400
0#
#17948700
b1101111 4
1#
#17982000
0#
#18015300
b1110000 4
1#
#18048600
0#
#18081900
b1110001 4
1#
#18115200
0#
#18148500
b1110010 4
1#
#18181800
0#
#18215100
b1110011 4
1#
#18248400
0#
#18281700
b1110100 4
1#
#18315000
0#
#18348300
b1110101 4
1#
#18381600
0#
#18414900
b1110110 4
1#
#18448200
0#
#18481500
b1110111 4
1#
#18514800
0#
#18548100
b1111000 4
1#
#18581400
0#
#18614700
b1111001 4
1#
#18648000
0#
#18681300
b1111010 4
1#
#18714600
0#
#18747900
b1111011 4
1#
#18781200
0#
#18814500
b1111100 4
1#
#18847800
0#
#18881100
b1111101 4
1#
#18914400
0#
#18947700
b1111110 4
1#
#18981000
0#
#19014300
b1111111 4
1#
#19047600
0#
#19080900
b10000000 4
1#
#19114200
0#
#19147500
b10000001 4
1#
#19180800
0#
#19214100
b10000010 4
1#
#19247400
0#
#19280700
b10000011 4
1#
#19314000
0#
#19347300
b10000100 4
1#
#19380600
0#
#19413900
b10000101 4
1#
#19447200
0#
#19480500
b10000110 4
1#
#19513800
0#
#19547100
b10000111 4
1#
#19580400
0#
#19613700
b10001000 4
1#
#19647000
0#
#19680300
b10001001 4
1#
#19713600
0#
#19746900
b10001010 4
1#
#19780200
0#
#19813500
b10001011 4
1#
#19846800
0#
#19880100
b10001100 4
1#
#19913400
0#
#19946700
b10001101 4
1#
#19980000
0#
#20013300
b10001110 4
1#
#20046600
0#
#20079900
b10001111 4
1#
#20113200
0#
#20146500
b10010000 4
1#
#20179800
0#
#20213100
b10010001 4
1#
#20246400
0#
#20279700
b10010010 4
1#
#20313000
0#
#20346300
b10010011 4
1#
#20379600
0#
#20412900
b10010100 4
1#
#20446200
0#
#20479500
b10010101 4
1#
#20512800
0#
#20546100
b10010110 4
1#
#20579400
0#
#20612700
b10010111 4
1#
#20646000
0#
#20679300
b10011000 4
1#
#20712600
0#
#20745900
b10011001 4
1#
#20779200
0#
#20812500
b10011010 4
1#
#20845800
0#
#20879100
b10011011 4
1#
#20912400
0#
#20945700
b1 3
b0 4
1#
#20979000
0#
#21012300
b1 4
1#
#21045600
0#
#21078900
b10 4
1#
#21112200
0#
#21145500
b11 4
1#
#21178800
0#
#21212100
b100 4
1#
#21245400
0#
#21278700
b101 4
1#
#21312000
0#
#21345300
b110 4
1#
#21378600
0#
#21411900
b111 4
1#
#21445200
0#
#21478500
b1000 4
1#
#21511800
0#
#21545100
b1001 4
1#
#21578400
0#
#21611700
b1010 4
1#
#21645000
0#
#21678300
b1011 4
1#
#21711600
0#
#21744900
b1100 4
1#
#21778200
0#
#21811500
b1101 4
1#
#21844800
0#
#21878100
b1110 4
1#
#21911400
0#
#21944700
b1111 4
1#
#21978000
0#
#22011300
b10000 4
1#
#22044600
0#
#22077900
b10001 4
1#
#22111200
0#
#22144500
b10010 4
1#
#22177800
0#
#22211100
b10011 4
1#
#22244400
0#
#22277700
b10100 4
1#
#22311000
0#
#22344300
b10101 4
1#
#22377600
0#
#22410900
b10110 4
1#
#22444200
0#
#22477500
b10111 4
1#
#22510800
0#
#22544100
b11000 4
1#
#22577400
0#
#22610700
b11001 4
1#
#22644000
0#
#22677300
b11010 4
1#
#22710600
0#
#22743900
b11011 4
1#
#22777200
0#
#22810500
b11100 4
1#
#22843800
0#
#22877100
b11101 4
1#
#22910400
0#
#22943700
b11110 4
1#
#22977000
0#
#23010300
b11111 4
1#
#23043600
0#
#23076900
b100000 4
1#
#23110200
0#
#23143500
b100001 4
1#
#23176800
0#
#23210100
b100010 4
1#
#23243400
0#
#23276700
b100011 4
1#
#23310000
0#
#23343300
b100100 4
1#
#23376600
0#
#23409900
b100101 4
1#
#23443200
0#
#23476500
b100110 4
1#
#23509800
0#
#23543100
b100111 4
1#
#23576400
0#
#23609700
b101000 4
1#
#23643000
0#
#23676300
b101001 4
1#
#23709600
0#
#23742900
b101010 4
1#
#23776200
0#
#23809500
b101011 4
1#
#23842800
0#
#23876100
b101100 4
1#
#23909400
0#
#23942700
b101101 4
1#
#23976000
0#
#24009300
b101110 4
1#
#24042600
0#
#24075900
b101111 4
1#
#24109200
0#
#24142500
b110000 4
1#
#24175800
0#
#24209100
b110001 4
1#
#24242400
0#
#24275700
b110010 4
1#
#24309000
0#
#24342300
b110011 4
1#
#24375600
0#
#24408900
b110100 4
1#
#24442200
0#
#24475500
b110101 4
1#
#24508800
0#
#24542100
b110110 4
1#
#24575400
0#
#24608700
b110111 4
1#
#24642000
0#
#24675300
b111000 4
1#
#24708600
0#
#24741900
b111001 4
1#
#24775200
0#
#24808500
b111010 4
1#
#24841800
0#
#24875100
b111011 4
1#
#24908400
0#
#24941700
b111100 4
1#
#24975000
0#
#25008300
b111101 4
1#
#25041600
0#
#25074900
b111110 4
1#
#25108200
0#
#25141500
b111111 4
1#
#25174800
0#
#25208100
b1000000 4
1#
#25241400
0#
#25274700
b1000001 4
1#
#25308000
0#
#25341300
b1000010 4
1#
#25374600
0#
#25407900
b1000011 4
1#
#25441200
0#
#25474500
b1000100 4
1#
#25507800
0#
#25541100
b1000101 4
1#
#25574400
0#
#25607700
b1000110 4
1#
#25641000
0#
#25674300
b1000111 4
1#
#25707600
0#
#25740900
b1001000 4
1#
#25774200
0#
#25807500
b1001001 4
1#
#25840800
0#
#25874100
b1001010 4
1#
#25907400
0#
#25940700
b1001011 4
1#
#25974000
0#
#26007300
b1001100 4
1#
#26040600
0#
#26073900
b1001101 4
1#
#26107200
0#
#26140500
b1001110 4
1#
#26173800
0#
#26207100
b1001111 4
1#
#26240400
0#
#26273700
b1010000 4
1#
#26307000
0#
#26340300
b1010001 4
1#
#26373600
0#
#26406900
b1010010 4
1#
#26440200
0#
#26473500
b1010011 4
1#
#26506800
0#
#26540100
b1010100 4
1#
#26573400
0#
#26606700
b1010101 4
1#
#26640000
0#
#26673300
b1010110 4
1#
#26706600
0#
#26739900
b1010111 4
1#
#26773200
0#
#26806500
b1011000 4
1#
#26839800
0#
#26873100
b1011001 4
1#
#26906400
0#
#26939700
b1011010 4
1#
#26973000
0#
#27006300
b1011011 4
1#
#27039600
0#
#27072900
b1011100 4
1#
#27106200
0#
#27139500
b1011101 4
1#
#27172800
0#
#27206100
b1011110 4
1#
#27239400
0#
#27272700
b1011111 4
1#
#27306000
0#
#27339300
b1100000 4
1#
#27372600
0#
#27405900
b1100001 4
1#
#27439200
0#
#27472500
b1100010 4
1#
#27505800
0#
#27539100
b1100011 4
1#
#27572400
0#
#27605700
b1100100 4
1#
#27639000
0#
